odoo/addons/eater/README.rst
odoo/addons/eater/__init__.py
odoo/addons/eater/__manifest__.py
odoo/addons/eater/demo/eaters.xml
odoo/addons/eater/i18n/eater.pot
odoo/addons/eater/i18n/fr.po
odoo/addons/eater/models/__init__.py
odoo/addons/eater/models/partner.py
odoo/addons/eater/readme/CONTRIBUTORS.rst
odoo/addons/eater/readme/DESCRIPTION.rst
odoo/addons/eater/static/description/index.html
odoo/addons/eater/static/font/Roboto-Bold.ttf
odoo/addons/eater/static/font/Roboto-Regular.ttf
odoo/addons/eater/static/src/img/blueline.png
odoo/addons/eater/static/src/img/logo.png
odoo/addons/eater/static/src/img/redline.png
odoo/addons/eater/views/partner.xml
odoo/addons/eater/wizard/__init__.py
odoo/addons/eater/wizard/new_eater_wizard.py
odoo/addons/eater/wizard/new_eater_wizard_views.xml
odoo12_addon_eater-12.0.1.0.0.99.dev14.dist-info/METADATA
odoo12_addon_eater-12.0.1.0.0.99.dev14.dist-info/WHEEL
odoo12_addon_eater-12.0.1.0.0.99.dev14.dist-info/top_level.txt
odoo12_addon_eater-12.0.1.0.0.99.dev14.dist-info/RECORD
