Metadata-Version: 2.1
Name: odoo12-addon-eater
Version: 12.0.1.0.0.99.dev14
Summary: Add eaters to the workers of your structure.
Home-page: https://github.com/beescoop/Obeesdoo
Author: BEES coop - Cellule IT, Coop IT Easy SC
License: AGPL-3
Platform: UNKNOWN
Classifier: Programming Language :: Python
Classifier: Framework :: Odoo
Classifier: Framework :: Odoo :: 12.0
Classifier: License :: OSI Approved :: GNU Affero General Public License v3
Requires-Python: >=3.5
Requires-Dist: odoo12-addon-partner-firstname
Requires-Dist: odoo (<12.1dev,>=12.0a)
